pandas_slim/__init__.py
pandas_slim/core.py
pandas_slim-0.1.2.dist-info/licenses/LICENSE
pandas_slim-0.1.2.dist-info/METADATA
pandas_slim-0.1.2.dist-info/WHEEL
pandas_slim-0.1.2.dist-info/top_level.txt
pandas_slim-0.1.2.dist-info/RECORD
