Metadata-Version: 2.4
Name: pandas-slim
Version: 0.1.2
Summary: A Python library to reduce pandas DataFrame memory usage
Home-page: https://github.com/RemiOunadjela/pandas-slim
Author: Remi Ounadjela
Author-email: Remi Ounadjela <contact@example.com>
Project-URL: Homepage, https://github.com/RemiOunadjela/pandas-slim
Project-URL: Repository, https://github.com/RemiOunadjela/pandas-slim
Project-URL: Documentation, https://github.com/RemiOunadjela/pandas-slim#readme
Project-URL: Bug Tracker, https://github.com/RemiOunadjela/pandas-slim/issues
Keywords: pandas,memory,optimization,dataframe,data-science
Classifier: Development Status :: 3 - Alpha
Classifier: Intended Audience :: Developers
Classifier: License :: OSI Approved :: MIT License
Classifier: Operating System :: OS Independent
Classifier: Programming Language :: Python :: 3
Classifier: Programming Language :: Python :: 3.7
Classifier: Programming Language :: Python :: 3.8
Classifier: Programming Language :: Python :: 3.9
Classifier: Programming Language :: Python :: 3.10
Classifier: Programming Language :: Python :: 3.11
Classifier: Topic :: Scientific/Engineering
Classifier: Topic :: Software Development :: Libraries :: Python Modules
Requires-Python: >=3.7
License-File: LICENSE
Requires-Dist: pandas>=1.0.0
Requires-Dist: numpy>=1.18.0
Requires-Dist: tqdm>=4.0.0
Requires-Dist: scikit-learn>=0.24.0
Requires-Dist: matplotlib>=3.0.0
Provides-Extra: dev
Requires-Dist: pytest>=6.0; extra == "dev"
Requires-Dist: pytest-cov>=2.0; extra == "dev"
Requires-Dist: black>=21.0; extra == "dev"
Requires-Dist: flake8>=3.8; extra == "dev"
Requires-Dist: mypy>=0.910; extra == "dev"
Dynamic: author
Dynamic: home-page
Dynamic: license-file
Dynamic: requires-python
